dc_securex-3.3.1.dist-info/licenses/LICENSE
securex/__init__.py
securex/_disable_method.py
securex/client.py
securex/models.py
securex/__pycache__/__init__.cpython-312.pyc
securex/__pycache__/client.cpython-312.pyc
securex/__pycache__/models.cpython-312.pyc
securex/backup/__init__.py
securex/backup/manager.py
securex/backup/__pycache__/__init__.cpython-312.pyc
securex/backup/__pycache__/manager.cpython-312.pyc
securex/handlers/__init__.py
securex/handlers/channel.py
securex/handlers/member.py
securex/handlers/role.py
securex/handlers/__pycache__/__init__.cpython-312.pyc
securex/handlers/__pycache__/channel.cpython-312.pyc
securex/handlers/__pycache__/member.cpython-312.pyc
securex/handlers/__pycache__/role.cpython-312.pyc
securex/storage/__init__.py
securex/storage/base_storage.py
securex/storage/postgres_storage.py
securex/storage/sqlite_storage.py
securex/storage/storage_factory.py
securex/storage/__pycache__/__init__.cpython-312.pyc
securex/storage/__pycache__/base_storage.cpython-312.pyc
securex/storage/__pycache__/json_storage.cpython-312.pyc
securex/storage/__pycache__/postgres_storage.cpython-312.pyc
securex/storage/__pycache__/sqlite_storage.cpython-312.pyc
securex/storage/__pycache__/storage_factory.cpython-312.pyc
securex/utils/__init__.py
securex/utils/punishment.py
securex/utils/whitelist.py
securex/utils/__pycache__/__init__.cpython-312.pyc
securex/utils/__pycache__/punishment.cpython-312.pyc
securex/utils/__pycache__/whitelist.cpython-312.pyc
securex/workers/__init__.py
securex/workers/action_worker.py
securex/workers/cleanup_worker.py
securex/workers/guild_worker.py
securex/workers/log_worker.py
securex/workers/__pycache__/__init__.cpython-312.pyc
securex/workers/__pycache__/action_worker.cpython-312.pyc
securex/workers/__pycache__/cleanup_worker.cpython-312.pyc
securex/workers/__pycache__/guild_worker.cpython-312.pyc
securex/workers/__pycache__/log_worker.cpython-312.pyc
tests/README.md
tests/__init__.py
tests/test_coverage_client.py
tests/test_coverage_handlers.py
dc_securex-3.3.1.dist-info/METADATA
dc_securex-3.3.1.dist-info/WHEEL
dc_securex-3.3.1.dist-info/top_level.txt
dc_securex-3.3.1.dist-info/RECORD
