Metadata-Version: 2.4
Name: dc-securex
Version: 3.3.1
Summary: Backend-only Discord anti-nuke protection SDK
Home-page: https://github.com/yourusername/securex-antinuke-sdk
Author: SecureX Team
Author-email: SecureX Team <contact@securex.dev>
License: MIT
Project-URL: Homepage, https://github.com/yourusername/securex-antinuke-sdk
Project-URL: Repository, https://github.com/yourusername/securex-antinuke-sdk
Project-URL: Issues, https://github.com/yourusername/securex-antinuke-sdk/issues
Keywords: discord,bot,antinuke,security,protection,sdk
Classifier: Development Status :: 4 - Beta
Classifier: Intended Audience :: Developers
Classifier: Topic :: Software Development :: Libraries :: Python Modules
Classifier: Programming Language :: Python :: 3
Classifier: License :: OSI Approved :: MIT License
Classifier: Operating System :: OS Independent
Requires-Python: >=3.8
License-File: LICENSE
Requires-Dist: discord.py>=2.0.0
Requires-Dist: aiofiles>=23.0.0
Requires-Dist: aiosqlite>=0.17.0
Dynamic: author
Dynamic: home-page
Dynamic: license-file
Dynamic: requires-python
